PrefAPI/__init__.py
prefapi-0.2.0.dist-info/WHEEL
prefapi-0.2.0.dist-info/METADATA
prefapi-0.2.0.dist-info/RECORD
